{
  "0": [
    "the",
    "it",
    "to",
    "my",
    "on",
    "http",
    "twitter",
    "for",
    "you",
    "and",
    "is",
    "thanks"
  ],
  "1": [
    "you",
    "the",
    "to",
    "me",
    "it",
    "that",
    "my",
    "is",
    "of",
    "your",
    "and",
    "in"
  ],
  "2": [
    "day",
    "happy",
    "mother",
    "mothers",
    "mother day",
    "happy mother",
    "mothers day",
    "happy mothers",
    "day to",
    "mom",
    "to all",
    "all"
  ],
  "3": [
    "and",
    "to",
    "he",
    "my",
    "the",
    "me",
    "it",
    "she",
    "that",
    "of",
    "her",
    "but"
  ],
  "4": [
    "the",
    "to",
    "and",
    "it",
    "is",
    "on",
    "watching",
    "that",
    "of",
    "my",
    "in",
    "you"
  ],
  "5": [
    "to",
    "the",
    "you",
    "in",
    "it",
    "and",
    "my",
    "for",
    "be",
    "go",
    "is",
    "so"
  ],
  "6": [
    "my",
    "the",
    "and",
    "to",
    "it",
    "of",
    "is",
    "just",
    "for",
    "in",
    "have",
    "but"
  ],
  "7": [
    "to",
    "work",
    "and",
    "morning",
    "today",
    "day",
    "the",
    "sleep",
    "night",
    "at",
    "my",
    "bed"
  ]
}